conjure_python_client/__init__.py
conjure_python_client/_version.py
conjure_python_client/py.typed
conjure_python_client/_http/__init__.py
conjure_python_client/_http/configuration.py
conjure_python_client/_http/requests_client.py
conjure_python_client/_lib/__init__.py
conjure_python_client/_lib/case.py
conjure_python_client/_lib/sanitize.py
conjure_python_client/_lib/types.py
conjure_python_client/_serde/__init__.py
conjure_python_client/_serde/decoder.py
conjure_python_client/_serde/encoder.py
conjure_python_client-3.1.0.dist-info/LICENSE
conjure_python_client-3.1.0.dist-info/METADATA
conjure_python_client-3.1.0.dist-info/WHEEL
conjure_python_client-3.1.0.dist-info/top_level.txt
conjure_python_client-3.1.0.dist-info/RECORD
